{
    "timestamp":1514439962223,
    "code":200,
    "message":{

    },
    "exception":null,
    "data":{
        "id":"xprod347515",
        "name":"大川碳化工艺钻板DC-8572",
        "invoiceLimit":0,
        "firstLevelCategoryName":"日杂",
        "secondLevelCategoryName":"家居百货",
        "thirdLevelCategoryName":null,
        "fourthLevelCategoryName":"竹制菜板",
        "saleName":"大川碳化工艺钻板DC-8572",
        "inputTaxRate":17,
        "deductibleTaxRate":15,
        "brandName":"大川",
        "supplyChainStatus":2,
        "purchaseInsideNumber":1,
        "salesInsideNumber":1,
        "productCode":"1000063",
        "internationalCodes":[
            {
                "id":"xincode329488",
                "productId":"xprod347515",
                "internationalCode":"6953066185720",
                "barcodeType":1
            }
        ],
        "minUnit":"个",
        "purchasePrice":19.6,
        "suggestPrice":29.5,
        "deliveryDay":6,
        "sellFullCase":0,
        "fullCaseUnit":null,
        "fullCaseUnitId":null
    },
    "success":true
}