{
    "code": 200,
    "auditStatus":1,
    "branchCompanyId":"10000",
    "branchCompanyName":"测试子公司",
    "createTime":1513828287000,
    "createUserId":"0000000",
    "deleteStatus":0,
    "deliveryDay":10,
    "id":668,
    "lowestPrice":22,
    "minNumber":10,
    "preHarvestPinStatus":1,
    "productId":"xprod347938",
    "salesInsideNumber":2,
    "sellPricesInReview":{
        "auditStatus":1,
        "branchCompanyId":"9999",
        "branchCompanyName":"测试子公司",
        "deleteStatus":0,
        "deliveryDay":10,
        "id":668,
        "lowestPrice":23,
        "minNumber":8,
        "modifyTime":1513839418312,
        "modifyUserId":"222222",
        "preHarvestPinStatus":1,
        "productId":"xprod347938",
        "salesInsideNumber":2,
        "sellSectionPrices":[
            {
                "deleteStatus":0,
                "endNumber":21,
                "id":3,
                "price":24,
                "sellPriceId":668,
                "startNumber":8
            },
            {
                "deleteStatus":0,
                "endNumber":34,
                "id":4,
                "price":23,
                "sellPriceId":668,
                "startNumber":22
            },
            {
                "deleteStatus":0,
                "endNumber":2147483647,
                "id":5,
                "price":28,
                "sellPriceId":668,
                "startNumber":35
            }
        ],
        "status":1,
        "suggestPrice":1000
    },
    "sellSectionPrices":[
        {
            "deleteStatus":0,
            "endNumber":20,
            "id":1426,
            "price":24,
            "sellPriceId":668,
            "startNumber":10
        },
        {
            "deleteStatus":0,
            "endNumber":30,
            "id":1427,
            "price":23,
            "sellPriceId":668,
            "startNumber":21
        },
        {
            "deleteStatus":0,
            "endNumber":2147483647,
            "id":1428,
            "price":22,
            "sellPriceId":668,
            "startNumber":31
        }
    ],
    "status":1,
    "suggestPrice":12
}
